{
    "original_source": {
        "database(url)": "https://github.com/SAP/project-kb",
        "software_system(CPE)": [],
        "fix_commit": "https://github.com/pivotal-cf/spring-cloud-sso-connector/commit/9531430217eb95f9c70e1728d0213b605ffbaa2c",
        "version_end_excluding": {},
        "path": {
            "file_path": "src/main/java/io/pivotal/spring/cloud/SsoServiceCredentialsListener.java"
        }
    },
    "programming_language": "JAVA",
    "licences": {
        "database": "Apache",
        "affected_repository": "Apache License 2.0"
    },
    "related_vulnerability_entry": {
        "CVE": [],
        "CWE": []
    }
}