{
    "original_source": {
        "database(url)": "https://github.com/SAP/project-kb",
        "software_system(CPE)": [],
        "fix_commit": "https://github.com/apache/olingo-odata4/commit/ae416b56094b046a6c9882c67b7fb268b56f1644",
        "version_end_excluding": {},
        "path": {
            "file_path": "lib/server-core/src/main/java/org/apache/olingo/server/core/deserializer/xml/ODataXmlDeserializer.java"
        }
    },
    "programming_language": "JAVA",
    "licences": {
        "database": "Apache",
        "affected_repository": "Apache License 2.0"
    },
    "related_vulnerability_entry": {
        "CVE": [],
        "CWE": []
    }
}